etc_jupyterlab_telemetry_producer_demo/__init__.py
etc_jupyterlab_telemetry_producer_demo/_version.py
etc_jupyterlab_telemetry_producer_demo/application.py
etc_jupyterlab_telemetry_producer_demo/handlers.py
etc_jupyterlab_telemetry_producer_demo-0.1.1.data/data/etc/jupyter/jupyter_server_config.d/etc_jupyterlab_telemetry_producer_demo.json
etc_jupyterlab_telemetry_producer_demo-0.1.1.data/data/share/jupyter/labextensions/etc_jupyterlab_telemetry_producer_demo/package.json
etc_jupyterlab_telemetry_producer_demo-0.1.1.data/data/share/jupyter/labextensions/etc_jupyterlab_telemetry_producer_demo/static/133.2b6b5fa8134874550152.js
etc_jupyterlab_telemetry_producer_demo-0.1.1.data/data/share/jupyter/labextensions/etc_jupyterlab_telemetry_producer_demo/static/735.d3d2edf7f9d8c2d9ad62.js
etc_jupyterlab_telemetry_producer_demo-0.1.1.data/data/share/jupyter/labextensions/etc_jupyterlab_telemetry_producer_demo/static/747.56e194fd0b33459db8cb.js
etc_jupyterlab_telemetry_producer_demo-0.1.1.data/data/share/jupyter/labextensions/etc_jupyterlab_telemetry_producer_demo/static/763.e6fa950f7c6e8dd53bc3.js
etc_jupyterlab_telemetry_producer_demo-0.1.1.data/data/share/jupyter/labextensions/etc_jupyterlab_telemetry_producer_demo/static/remoteEntry.2f53b1007f9159e8c47a.js
etc_jupyterlab_telemetry_producer_demo-0.1.1.data/data/share/jupyter/labextensions/etc_jupyterlab_telemetry_producer_demo/static/style.js
etc_jupyterlab_telemetry_producer_demo-0.1.1.data/data/share/jupyter/labextensions/etc_jupyterlab_telemetry_producer_demo/static/third-party-licenses.json
etc_jupyterlab_telemetry_producer_demo-0.1.1.data/data/share/jupyter/labextensions/etc_jupyterlab_telemetry_producer_demo/install.json
etc_jupyterlab_telemetry_producer_demo-0.1.1.dist-info/METADATA
etc_jupyterlab_telemetry_producer_demo-0.1.1.dist-info/WHEEL
etc_jupyterlab_telemetry_producer_demo-0.1.1.dist-info/licenses/LICENSE
etc_jupyterlab_telemetry_producer_demo-0.1.1.dist-info/RECORD
